neighpy/__init__.py
neighpy/_mcintegrals.py
neighpy/appraise.py
neighpy/search.py
neighpy-0.1.8.dist-info/METADATA
neighpy-0.1.8.dist-info/WHEEL
neighpy-0.1.8.dist-info/licenses/LICENSE.rst
neighpy-0.1.8.dist-info/RECORD
