Metadata-Version: 2.4
Name: neighpy
Version: 0.1.8
Summary: Neighbourhood Algorithm in Python
License: GPL-3.0-or-later
License-File: LICENSE.rst
Author: auggiemarignier
Author-email: augustin.marignier@anu.edu.au
Requires-Python: >=3.10,<4.0
Classifier: License :: OSI Approved :: GNU General Public License v3 or later (GPLv3+)
Classifier: Programming Language :: Python :: 3
Classifier: Programming Language :: Python :: 3.10
Classifier: Programming Language :: Python :: 3.11
Classifier: Programming Language :: Python :: 3.12
Classifier: Programming Language :: Python :: 3.13
Classifier: Programming Language :: Python :: 3.14
Requires-Dist: joblib (>=1.3.2,<2.0.0)
Requires-Dist: numpy (>=1.22)
Requires-Dist: tqdm (>=4.66.2,<5.0.0)
Project-URL: Documentation, https://neighpy.readthedocs.io/en/latest/index.html
Project-URL: Homepage, https://github.com/auggiemarignier/neighpy
Project-URL: Repository, https://github.com/auggiemarignier/neighpy
